pawz_core-0.2.1.dist-info/METADATA
pawz_core-0.2.1.dist-info/WHEEL
pawz_core/__init__.py
pawz_core/pawz_core.cpython-311-darwin.so
pawz_core-0.2.1.dist-info/RECORD
